{"title":"C\u00f4ng vi\u00ean V\u00f5 Th\u1ecb S\u00e1u","subTitle":null,"isIndexed":true,"slug":"tuong-dai-vo-thi-sau","publish":true,"pro":false,"unlocked":false,"lng":107.2702415,"lat":10.4896995,"place_id":"ChIJX39qDkl1dTERRv0p5XOMsn0","config":{"design":{"themeConfig":{"selected":"basekrpano","config":{"primaryColor":"rgb(19,80,124)","textColor":"#ffffff","autoOpenSceneList":true,"positionTitle":"left"}},"hotspotConfig":{"keepHotspotPositionWhenZooming":true,"lockHotspot":true,"bgColor":"rgb(1,104,177)","hideTitleOnTopHotspot":true,"hotspotArticleLayout":"normal"},"formCaptureConfig":{"backgroundColor":"#fff","overlayColor":"#00000073","layout":{"type":"panel"}},"callToActionConfig":{"layout":"list","position":"left","offsetLeft":"12","offsetRight":"12"},"popupConfig":{"bgColor":"rgb(255,255,255)","textColor":"#000000"}},"setting":{"control_mode":{"mode":"drag"},"auto_rotate":{"enable":true,"wait_time":2,"speed":2},"auto_change_scene":{"enable":false},"intro_little_planet":{"enable":true},"follow_mode":{"enable":false},"projection_mode":{"mode":"little_planet"},"general":{"first_scene":"66f4c8ed0a46d037f35efa61"}},"marketing":{"meta_data":{"title":"IGB Group","description":"Demo Panorama","favicon":"static\/media\/asset\/PRXcMuYXIbo5LAp2fSKu.png"}}},"thumbnail":{"name":"3.-CV-Vo-Thi-Sau-1024x651","type":"asset","subType":"sphere","mimetype":"image\/jpeg","deleting":false,"archived":false,"size":908496,"isFolder":false,"userChild":null,"updated_at":"2024-09-26T09:10:03.140Z","created_at":"2024-09-26T09:09:42.490Z","src":"static\/media\/asset\/WGDeIDTxtEPj3myWxe1L.jpg","src_thumb":"static\/media\/asset\/thumb\/300x_ww8mUghIEp9l9eL26RES.webp","src_preview":null,"krpano_xml":null,"id":"66f524d6ae7bdf9c6286cb64"},"domain":null,"paymentStatus":null,"domainApi":null,"multiLangEnabled":false,"gsv_published":false,"gsv_message_id_queue":null,"duplicate_message_id_queue":null,"matterport_key":null,"matterport_space":null,"project_type":null,"exportSessions":null,"garbage":false,"category":"6491879e6b4ca2750b20c4a4","background_sound_multi_lang":null,"background_sound":{"name":"BietOnChiVoThiSau-HuyenTrang-4406429","type":"asset","subType":"sphere","mimetype":"audio\/mpeg","deleting":false,"archived":false,"size":4295403,"isFolder":false,"userChild":null,"updated_at":"2024-09-26T10:08:42.420Z","created_at":"2024-09-26T10:08:42.420Z","src":"static\/media\/asset\/paCwq0k4kPoEX4kuOwG9.mp3","src_thumb":null,"src_preview":null,"krpano_xml":null,"id":"66f532aaae7bdf20d286cbc0"},"background_sound_volume":0.4,"post":"66f52008ae7bdf25cb86cb27","user":"66f3e638ae7bdfd7f186be92","userChild":null,"updated_at":"2024-10-01T15:49:55.235Z","created_at":"2024-09-25T10:32:57.876Z","featured_image":"static\/media\/pano\/render\/M7yPapQP70WOaYq81nYp.png","first_scene":{"media":{"name":"panorama1","type":"pano","subType":"sphere","mimetype":"image\/jpeg","deleting":false,"archived":false,"size":3210367,"isFolder":false,"userChild":null,"updated_at":"2024-09-26T02:41:32.000Z","created_at":"2024-09-26T02:36:03.848Z","src":null,"src_thumb":"static\/media\/pano\/thumb\/300x_D2vCVVMTX5o4KZwR1Kj1.webp","src_preview":"static\/media\/pano\/preview\/4000x_0OjDw6M12kpNGGxXJIdc.webp","krpano_xml":"<preview url=\"static\/media\/pano\/vtour\/1727318466-6296\/preview.jpg\" \/><image><cube url=\"static\/media\/pano\/vtour\/1727318466-6296\/%s\/l%l\/%v\/l%l_%s_%v_%h.jpg\" multires=\"512,640,1280\" \/><\/image>","id":"66f4c893ae7bdf6e4c86c809"},"background_sound":null,"parent":null,"group":"66f4caefae7bdf7a8d86c820","project":"66f3e6d90a46d09e185ef0d4","post":null,"id":"66f4c8ed0a46d037f35efa61"},"scenes":[{"title":"C\u1ed5ng v\u00e0o","media":{"name":"panorama1","type":"pano","subType":"sphere","mimetype":"image\/jpeg","deleting":false,"archived":false,"size":3210367,"isFolder":false,"userChild":null,"updated_at":"2024-09-26T02:41:32.000Z","created_at":"2024-09-26T02:36:03.848Z","src":null,"src_thumb":"static\/media\/pano\/thumb\/300x_D2vCVVMTX5o4KZwR1Kj1.webp","src_preview":"static\/media\/pano\/preview\/4000x_0OjDw6M12kpNGGxXJIdc.webp","krpano_xml":"<preview url=\"static\/media\/pano\/vtour\/1727318466-6296\/preview.jpg\" \/><image><cube url=\"static\/media\/pano\/vtour\/1727318466-6296\/%s\/l%l\/%v\/l%l_%s_%v_%h.jpg\" multires=\"512,640,1280\" \/><\/image>","id":"66f4c893ae7bdf6e4c86c809"},"background_sound_multi_lang":null,"background_sound":null,"background_sound_volume":0.8,"mode":"","parent":null,"lat":21.0050858,"lng":105.8552739,"gsv_id":null,"gsv_url":null,"gsv_hidden":false,"gsv_heading":[0,0],"gsv_errs":[],"sort_in_parent":0,"mode_in_parent":"","north_ath":null,"north_atv":null,"sort":0,"count_view":0,"publish":true,"configPlugin":{"pp_sharpen":{"enabled":false},"pp_light":{"enabled":false}},"group":"66f4caefae7bdf7a8d86c820","project":"66f3e6d90a46d09e185ef0d4","post":null,"updated_at":"2024-10-01T08:43:12.162Z","created_at":"2024-09-26T02:37:33.415Z","hotspots":[{"title":"T\u01b0\u1ee3ng \u0111\u00e0i V\u00f5 Th\u1ecb S\u00e1u","type":"point","icon":null,"width":50,"height":50,"atv":-3.349508236000499,"ath":-9.474068155484758,"x":0,"y":0,"z":0,"config":{"style":{"type":"callout","effect":"pulse-grow","rotate":0,"opacity":100,"size":3,"callout":{"type":"image","degrees":45,"src":"static\/media\/asset\/WGDeIDTxtEPj3myWxe1L.jpg"}},"point":{"target_scene_id":"66f4c8edae7bdf3e0e86c811"}},"polygon":false,"post":null,"itemPrd":null,"updated_at":"2024-10-01T08:43:12.162Z","created_at":"2024-10-01T08:32:35.381Z","id":"66fbb3a35fd3134dbf7d8724"},{"title":"S\u00e2n ch\u00ednh","type":"point","icon":null,"width":50,"height":50,"atv":30.7633089860064,"ath":-5.935807554034454,"x":0,"y":0,"z":0,"config":{"style":{"type":"image","effect":"normal","rotate":0,"opacity":100,"size":"4","image":{"src":"static\/media\/hotspot-image\/Y1W0c3mJXygsuh5GfCm8.png"}},"point":{"title_on_top_hide":true,"preview_box_hide":false,"target_scene_id":"66f4c8edae7bdfe70c86c810","hlookat_default":0,"vlookat_default":0,"zoom_default":90,"isTransition":true,"typeTransition":"3d"}},"polygon":false,"post":null,"itemPrd":null,"updated_at":"2024-10-01T08:40:37.940Z","created_at":"2024-09-26T06:52:12.854Z","id":"66f5049cae7bdf286a86c962"}],"commentScenes":[],"id":"66f4c8ed0a46d037f35efa61"},{"title":"S\u00e2n ch\u00ednh","media":{"name":"panorama2","type":"pano","subType":"sphere","mimetype":"image\/jpeg","deleting":false,"archived":false,"size":890753,"isFolder":false,"userChild":null,"updated_at":"2024-09-26T02:41:47.000Z","created_at":"2024-09-26T02:36:27.077Z","src":null,"src_thumb":"static\/media\/pano\/thumb\/300x_3wWbjjB83Eznvmp3zufs.webp","src_preview":"static\/media\/pano\/preview\/4000x_TGRttMhNAhpwAeejc8qO.webp","krpano_xml":"<preview url=\"static\/media\/pano\/vtour\/1727318493-4144\/preview.jpg\" \/><image><cube url=\"static\/media\/pano\/vtour\/1727318493-4144\/%s\/l%l\/%v\/l%l_%s_%v_%h.jpg\" multires=\"512,768\" \/><\/image>","id":"66f4c8ab0a46d023d05efa56"},"background_sound_multi_lang":null,"background_sound":null,"background_sound_volume":0.8,"mode":"","parent":null,"lat":null,"lng":null,"gsv_id":null,"gsv_url":null,"gsv_hidden":false,"gsv_heading":[0,0],"gsv_errs":[],"sort_in_parent":0,"mode_in_parent":"","north_ath":null,"north_atv":null,"sort":1,"count_view":0,"publish":true,"group":"66f4caefae7bdf7a8d86c820","project":"66f3e6d90a46d09e185ef0d4","post":null,"updated_at":"2024-09-27T02:42:36.140Z","created_at":"2024-09-26T02:37:33.389Z","hotspots":[{"title":"T\u01b0\u1ee3ng \u0111\u00e0i V\u00f5 Th\u1ecb S\u00e1u","type":"point","icon":null,"width":50,"height":50,"atv":12.444762592763041,"ath":0.8316832006040045,"x":0,"y":0,"z":0,"config":{"style":{"type":"image","effect":"normal","rotate":0,"opacity":100,"size":3,"image":{"src":"static\/media\/hotspot-image\/WWDmMkpTTQ2dusZKQkV5.png"}},"point":{"title_on_top_hide":true,"target_scene_id":"66f4c8edae7bdf3e0e86c811"}},"polygon":false,"post":null,"itemPrd":null,"updated_at":"2024-09-27T02:42:36.140Z","created_at":"2024-09-27T02:40:31.190Z","id":"66f61b1fae7bdf61b886d5c3"},{"title":"C\u1ed5ng v\u00e0o","type":"point","icon":null,"width":50,"height":50,"atv":14.93045510320593,"ath":-178.88565733340624,"x":0,"y":0,"z":0,"config":{"style":{"type":"image","effect":"normal","rotate":0,"opacity":100,"size":3,"image":{"src":"static\/media\/hotspot-image\/WWDmMkpTTQ2dusZKQkV5.png"}},"point":{"title_on_top_hide":true,"preview_box_hide":true,"target_scene_id":"66f4c8ed0a46d037f35efa61"}},"polygon":false,"post":null,"itemPrd":null,"updated_at":"2024-09-27T02:42:20.919Z","created_at":"2024-09-27T02:41:36.736Z","id":"66f61b600a46d067b25f0969"}],"commentScenes":[],"id":"66f4c8edae7bdfe70c86c810"},{"title":"T\u01b0\u1ee3ng \u0111\u00e0i V\u00f5 Th\u1ecb S\u00e1u","media":{"name":"panorama3","type":"pano","subType":"sphere","mimetype":"image\/jpeg","deleting":false,"archived":false,"size":3953445,"isFolder":false,"userChild":null,"updated_at":"2024-09-26T02:42:34.000Z","created_at":"2024-09-26T02:36:34.017Z","src":null,"src_thumb":"static\/media\/pano\/thumb\/300x_J3DEzzYwakCJGXZOzWXs.webp","src_preview":"static\/media\/pano\/preview\/4000x_QarN5mLYHPZFCIXOzAaA.webp","krpano_xml":"<preview url=\"static\/media\/pano\/vtour\/1727318520-5591\/preview.jpg\" \/><image><cube url=\"static\/media\/pano\/vtour\/1727318520-5591\/%s\/l%l\/%v\/l%l_%s_%v_%h.jpg\" multires=\"512,1024,1792\" \/><\/image>","id":"66f4c8b2ae7bdfdab186c80b"},"background_sound_multi_lang":null,"background_sound":null,"background_sound_volume":0.8,"mode":"","parent":null,"lat":null,"lng":null,"gsv_id":null,"gsv_url":null,"gsv_hidden":false,"gsv_heading":[0,0],"gsv_errs":[],"sort_in_parent":0,"mode_in_parent":"","north_ath":null,"north_atv":null,"sort":2,"count_view":0,"publish":true,"group":"66f4caefae7bdf7a8d86c820","project":"66f3e6d90a46d09e185ef0d4","post":"66f61e740a46d084af5f097a","updated_at":"2024-09-27T03:08:47.774Z","created_at":"2024-09-26T02:37:33.393Z","hotspots":[{"title":"L\u1ed1i l\u00ean nh\u00e0 t\u01b0\u1edfng ni\u1ec7m","type":"point","icon":null,"width":50,"height":50,"atv":-19.46453338104662,"ath":31.35449735134921,"x":0,"y":0,"z":0,"config":{"style":{"type":"callout","effect":"normal","rotate":0,"opacity":100,"size":3,"callout":{"type":"image","degrees":45}},"point":{"target_scene_id":"66f4c8edae7bdf641e86c80f"}},"polygon":false,"post":null,"itemPrd":null,"updated_at":"2024-09-27T03:08:47.773Z","created_at":"2024-09-27T03:03:06.983Z","id":"66f6206a0a46d0708e5f0984"},{"title":"S\u00e2n ch\u00ednh","type":"point","icon":null,"width":50,"height":50,"atv":36.03597271788392,"ath":-174.62193397567904,"x":0,"y":0,"z":0,"config":{"style":{"type":"image","effect":"normal","rotate":0,"opacity":100,"size":3,"image":{"src":"static\/media\/hotspot-image\/WWDmMkpTTQ2dusZKQkV5.png"}},"point":{"target_scene_id":"66f4c8edae7bdfe70c86c810","title_on_top_hide":true}},"polygon":false,"post":null,"itemPrd":null,"updated_at":"2024-09-27T03:08:24.659Z","created_at":"2024-09-27T03:07:19.215Z","id":"66f62167ae7bdf8da186d5de"},{"title":"Gi\u1edbi thi\u1ec7u t\u01b0\u1ee3ng \u0111\u00e0i V\u00f5 Th\u1ecb S\u00e1u","type":"article","icon":null,"width":50,"height":50,"atv":21.5234569808005,"ath":16.946144380605006,"x":0,"y":0,"z":0,"config":{"style":{"type":"image","effect":"normal","rotate":0,"opacity":100,"size":3,"image":{"src":"static\/media\/hotspot-image\/3JSeYug9iNAH0cwi73Eo.png"}},"article":{"post_id":"66f61e740a46d084af5f097a"}},"polygon":false,"post":null,"itemPrd":null,"updated_at":"2024-09-27T02:59:24.684Z","created_at":"2024-09-27T02:56:43.715Z","id":"66f61eeb0a46d0d5465f0981"}],"commentScenes":[],"id":"66f4c8edae7bdf3e0e86c811"},{"title":"L\u1ed1i v\u00e0o khu t\u01b0\u1edfng ni\u1ec7m","media":{"name":"panorama4","type":"pano","subType":"sphere","mimetype":"image\/jpeg","deleting":false,"archived":false,"size":689587,"isFolder":false,"userChild":null,"updated_at":"2024-09-26T02:42:47.000Z","created_at":"2024-09-26T02:36:50.223Z","src":null,"src_thumb":"static\/media\/pano\/thumb\/300x_PBRgMIQBkl4BotEklAFu.webp","src_preview":"static\/media\/pano\/preview\/4000x_Dis4nrbVttobrnwF7A4u.webp","krpano_xml":"<preview url=\"static\/media\/pano\/vtour\/1727318554-9173\/preview.jpg\" \/><image><cube url=\"static\/media\/pano\/vtour\/1727318554-9173\/%s\/l%l\/%v\/l%l_%s_%v_%h.jpg\" multires=\"512,768\" \/><\/image>","id":"66f4c8c20a46d00b015efa58"},"background_sound_multi_lang":null,"background_sound":null,"background_sound_volume":0.8,"mode":"","parent":null,"lat":null,"lng":null,"gsv_id":null,"gsv_url":null,"gsv_hidden":false,"gsv_heading":[0,0],"gsv_errs":[],"sort_in_parent":0,"mode_in_parent":"","north_ath":null,"north_atv":null,"sort":3,"count_view":0,"publish":true,"configPlugin":{"pp_sharpen":{"enabled":false}},"group":"66f4caefae7bdf7a8d86c820","project":"66f3e6d90a46d09e185ef0d4","post":null,"updated_at":"2024-10-01T08:26:43.967Z","created_at":"2024-09-26T02:37:33.386Z","hotspots":[{"title":"Gi\u1edbi thi\u1ec7u \u0111\u1ec1n th\u1edd ch\u00ednh \u0111i\u1ec7n","type":"article","icon":null,"width":50,"height":50,"atv":21.027312233690445,"ath":-42.500614806502995,"x":0,"y":0,"z":0,"config":{"style":{"type":"image","effect":"normal","rotate":0,"opacity":100,"size":3,"image":{"src":"static\/media\/hotspot-image\/3JSeYug9iNAH0cwi73Eo.png"}},"article":{"post_id":"66f627790a46d00b055f0999"}},"polygon":false,"post":null,"itemPrd":null,"updated_at":"2024-09-27T03:36:50.333Z","created_at":"2024-09-27T03:12:12.988Z","id":"66f6228cae7bdf833486d5e1"},{"title":"T\u01b0\u1ee3ng \u0111\u00e0i V\u00f5 Th\u1ecb S\u00e1u","type":"point","icon":null,"width":50,"height":50,"atv":10.015376014738665,"ath":169.65426102044347,"x":0,"y":0,"z":0,"config":{"style":{"type":"image","effect":"normal","rotate":0,"opacity":100,"size":3,"image":{"src":"static\/media\/hotspot-image\/h8LIynbHAGxOnK7ZLFPr.png"}},"point":{"target_scene_id":"66f4c8edae7bdf3e0e86c811"}},"polygon":false,"post":null,"itemPrd":null,"updated_at":"2024-09-27T03:17:24.941Z","created_at":"2024-09-27T03:16:06.780Z","id":"66f623760a46d02ff95f0987"},{"title":"\u0110\u1ec1n th\u1edd ch\u00ednh \u0111i\u1ec7n","type":"point","icon":null,"width":50,"height":50,"atv":-1.0954152755241524,"ath":-8.04094779130628,"x":0,"y":0,"z":0,"config":{"style":{"type":"image","effect":"normal","rotate":0,"opacity":100,"size":3,"image":{"src":"static\/media\/hotspot-image\/WWDmMkpTTQ2dusZKQkV5.png"}},"point":{"target_scene_id":"66f4c8ed0a46d08d955efa60","isTransition":true,"typeTransition":"3d"}},"polygon":false,"post":null,"itemPrd":null,"updated_at":"2024-09-27T03:15:20.366Z","created_at":"2024-09-27T03:10:31.972Z","id":"66f622270a46d032dd5f0985"}],"commentScenes":[],"id":"66f4c8edae7bdf641e86c80f"},{"title":"\u0110\u1ec1n th\u1edd ch\u00ednh \u0111i\u1ec7n","media":{"name":"panorama5","type":"pano","subType":"sphere","mimetype":"image\/jpeg","deleting":false,"archived":false,"size":3049380,"isFolder":false,"userChild":null,"updated_at":"2024-09-26T02:42:30.000Z","created_at":"2024-09-26T02:37:01.097Z","src":null,"src_thumb":"static\/media\/pano\/thumb\/300x_UoDjbmLgYmpLYGSedW16.webp","src_preview":"static\/media\/pano\/preview\/4000x_IIGf0jtMBoJT7jyVIF2R.webp","krpano_xml":"<preview url=\"static\/media\/pano\/vtour\/1727318507-5841\/preview.jpg\" \/><image><cube url=\"static\/media\/pano\/vtour\/1727318507-5841\/%s\/l%l\/%v\/l%l_%s_%v_%h.jpg\" multires=\"512,1024,1792\" \/><\/image>","id":"66f4c8cdae7bdf8de586c80d"},"background_sound_multi_lang":null,"background_sound":null,"background_sound_volume":0.8,"mode":"","parent":null,"lat":null,"lng":null,"gsv_id":null,"gsv_url":null,"gsv_hidden":false,"gsv_heading":[0,0],"gsv_errs":[],"sort_in_parent":0,"mode_in_parent":"","north_ath":null,"north_atv":null,"sort":4,"count_view":0,"publish":true,"group":"66f4cb190a46d0ebac5efa69","project":"66f3e6d90a46d09e185ef0d4","post":null,"updated_at":"2024-09-27T03:23:17.369Z","created_at":"2024-09-26T02:37:33.411Z","hotspots":[{"title":"Khu t\u01b0\u1edfng ni\u1ec7m 2","type":"point","icon":null,"width":50,"height":50,"atv":9.064195232090537,"ath":33.19226228212034,"x":0,"y":0,"z":0,"config":{"style":{"type":"icon","effect":"normal","rotate":0,"opacity":100,"size":3,"lottie":{"loop":true},"callout":{"type":"image","degrees":45}},"point":{"target_scene_id":"66f4c8ed0a46d006f45efa5f"}},"polygon":false,"post":null,"itemPrd":null,"updated_at":"2024-09-27T03:23:17.369Z","created_at":"2024-09-27T03:22:48.293Z","id":"66f62508ae7bdf62ad86d5e8"},{"title":"Khu t\u01b0\u1edfng ni\u1ec7m 1","type":"point","icon":null,"width":50,"height":50,"atv":7.437112764149725,"ath":-54.826999174028856,"x":0,"y":0,"z":0,"config":{"style":{"type":"icon","effect":"normal","rotate":0,"opacity":100,"size":3,"lottie":{"loop":true},"callout":{"type":"image","degrees":45}},"point":{"target_scene_id":"66f4c8ed0a46d022d85efa5e"}},"polygon":false,"post":null,"itemPrd":null,"updated_at":"2024-09-27T03:23:15.727Z","created_at":"2024-09-27T03:21:29.707Z","id":"66f624b9ae7bdf32f286d5e7"},{"title":"Khu t\u01b0\u1edfng ni\u1ec7m","type":"point","icon":null,"width":50,"height":50,"atv":20.267646619810716,"ath":-11.665928725451238,"x":0,"y":0,"z":0,"config":{"style":{"type":"image","effect":"normal","rotate":0,"opacity":100,"size":3,"image":{"src":"static\/media\/hotspot-image\/KuCPL9d13GfPcoZGl5qn.png"}},"point":{"target_scene_id":"66f4c8edae7bdf641e86c80f"}},"polygon":false,"post":null,"itemPrd":null,"updated_at":"2024-09-27T03:21:02.062Z","created_at":"2024-09-27T03:20:22.876Z","id":"66f624760a46d0414c5f098c"}],"commentScenes":[],"id":"66f4c8ed0a46d08d955efa60"},{"title":"Khu t\u01b0\u1edfng ni\u1ec7m 1","media":{"name":"panorama6","type":"pano","subType":"sphere","mimetype":"image\/jpeg","deleting":false,"archived":false,"size":517383,"isFolder":false,"userChild":null,"updated_at":"2024-09-26T02:42:47.000Z","created_at":"2024-09-26T02:37:10.550Z","src":null,"src_thumb":"static\/media\/pano\/thumb\/300x_mHVjzUOIVArpeISLCnON.webp","src_preview":"static\/media\/pano\/preview\/4000x_woc1O5OM4oF1N6eDkeE7.webp","krpano_xml":"<preview url=\"static\/media\/pano\/vtour\/1727318552-3079\/preview.jpg\" \/><image><cube url=\"static\/media\/pano\/vtour\/1727318552-3079\/%s\/l%l\/%v\/l%l_%s_%v_%h.jpg\" multires=\"512,768\" \/><\/image>","id":"66f4c8d60a46d0673c5efa5a"},"background_sound_multi_lang":null,"background_sound":null,"background_sound_volume":0.8,"mode":"","parent":null,"lat":null,"lng":null,"gsv_id":null,"gsv_url":null,"gsv_hidden":false,"gsv_heading":[0,0],"gsv_errs":[],"sort_in_parent":0,"mode_in_parent":"","north_ath":null,"north_atv":null,"sort":5,"count_view":0,"publish":true,"group":"66f4cb190a46d0ebac5efa69","project":"66f3e6d90a46d09e185ef0d4","post":null,"updated_at":"2024-10-01T08:51:13.357Z","created_at":"2024-09-26T02:37:33.409Z","hotspots":[{"title":"Khu t\u01b0\u1edfng ni\u1ec7m 2","type":"point","icon":null,"width":50,"height":50,"atv":11.20104740488403,"ath":169.73718004894448,"x":0,"y":0,"z":0,"config":{"style":{"type":"image","effect":"normal","rotate":0,"opacity":100,"size":3,"image":{"src":"static\/media\/hotspot-image\/X9Tv65D85uClgmPK3Bwe.png"}},"point":{"target_scene_id":"66f4c8ed0a46d006f45efa5f"}},"polygon":false,"post":null,"itemPrd":null,"updated_at":"2024-10-01T08:51:13.356Z","created_at":"2024-09-27T03:26:43.126Z","id":"66f625f3ae7bdf127086d5f2"},{"title":"L\u1ed1i v\u00e0o khu t\u01b0\u1edfng ni\u1ec7m","type":"point","icon":null,"width":50,"height":50,"atv":21.990943426234697,"ath":167.69442585721603,"x":0,"y":0,"z":0,"config":{"style":{"type":"image","effect":"normal","rotate":0,"opacity":100,"size":3,"image":{"src":"static\/media\/hotspot-image\/ZJ3k8WNkCeKCCOyNGvRK.png"}},"point":{"title_on_top_hide":true,"preview_box_hide":true,"target_scene_id":"66f4c8edae7bdf641e86c80f"}},"polygon":false,"post":null,"itemPrd":null,"updated_at":"2024-09-27T03:31:27.527Z","created_at":"2024-09-27T03:30:05.264Z","id":"66f626bd0a46d0dfb45f0997"},{"title":"\u0110\u1ec1n th\u1edd ch\u00ednh \u0111i\u1ec7n","type":"point","icon":null,"width":50,"height":50,"atv":16.826966474250533,"ath":-142.65379334074453,"x":0,"y":0,"z":0,"config":{"style":{"type":"image","effect":"normal","rotate":0,"opacity":100,"size":3,"image":{"src":"static\/media\/hotspot-image\/lrVxK89PGNgd87Q9tvWA.png"}},"point":{"target_scene_id":"66f4c8ed0a46d08d955efa60"}},"polygon":false,"post":null,"itemPrd":null,"updated_at":"2024-09-27T03:29:23.723Z","created_at":"2024-09-27T03:28:02.587Z","id":"66f626420a46d022145f0993"},{"title":"Gi\u1edbi thi\u1ec7u khu t\u01b0\u1edfng ni\u1ec7m","type":"article","icon":null,"width":50,"height":50,"atv":-4.186872332484526,"ath":-10.770847676067774,"x":0,"y":0,"z":0,"config":{"style":{"type":"icon","effect":"normal","rotate":0,"opacity":100,"size":3,"lottie":{"loop":true},"callout":{"type":"image","degrees":45}},"article":{"post_id":"66f625b3ae7bdf827f86d5ee","title_on_top_hide":true,"preview_box_hide":true}},"polygon":false,"post":null,"itemPrd":null,"updated_at":"2024-09-27T03:25:58.206Z","created_at":"2024-09-27T03:24:29.355Z","id":"66f6256dae7bdfef3986d5ea"}],"commentScenes":[],"id":"66f4c8ed0a46d022d85efa5e"},{"title":"Khu t\u01b0\u1edfng ni\u1ec7m 2","media":{"name":"panorama7","type":"pano","subType":"sphere","mimetype":"image\/jpeg","deleting":false,"archived":false,"size":529287,"isFolder":false,"userChild":null,"updated_at":"2024-09-26T02:42:59.000Z","created_at":"2024-09-26T02:37:26.065Z","src":null,"src_thumb":"static\/media\/pano\/thumb\/300x_QsEHnJxWVYtr0x4QKvcM.webp","src_preview":"static\/media\/pano\/preview\/4000x_qkxhoxCkAeYTIRCGSwqI.webp","krpano_xml":"<preview url=\"static\/media\/pano\/vtour\/1727318567-1505\/preview.jpg\" \/><image><cube url=\"static\/media\/pano\/vtour\/1727318567-1505\/%s\/l%l\/%v\/l%l_%s_%v_%h.jpg\" multires=\"512,768\" \/><\/image>","id":"66f4c8e60a46d0fc415efa5c"},"background_sound_multi_lang":null,"background_sound":null,"background_sound_volume":0.8,"mode":"","parent":null,"lat":null,"lng":null,"gsv_id":null,"gsv_url":null,"gsv_hidden":false,"gsv_heading":[0,0],"gsv_errs":[],"sort_in_parent":0,"mode_in_parent":"","north_ath":null,"north_atv":null,"sort":6,"count_view":0,"publish":true,"group":"66f4cb190a46d0ebac5efa69","project":"66f3e6d90a46d09e185ef0d4","post":null,"updated_at":"2024-09-27T03:34:56.048Z","created_at":"2024-09-26T02:37:33.411Z","hotspots":[{"title":"\u0110\u1ec1n th\u1edd ch\u00ednh \u0111i\u1ec7n","type":"point","icon":null,"width":50,"height":50,"atv":15.226514419581987,"ath":-121.47043249078735,"x":0,"y":0,"z":0,"config":{"style":{"type":"image","effect":"normal","rotate":0,"opacity":100,"size":3,"image":{"src":"static\/media\/hotspot-image\/lrVxK89PGNgd87Q9tvWA.png"}},"point":{"target_scene_id":"66f4c8ed0a46d08d955efa60"}},"polygon":false,"post":null,"itemPrd":null,"updated_at":"2024-09-27T03:34:56.048Z","created_at":"2024-09-27T03:34:06.490Z","id":"66f627ae0a46d033f45f099a"},{"title":"Gi\u1edbi thi\u1ec7u khu t\u01b0\u1edfng ni\u1ec7m","type":"article","icon":null,"width":50,"height":50,"atv":-5.898818773042588,"ath":77.21320191190284,"x":0,"y":0,"z":0,"config":{"style":{"type":"image","effect":"normal","rotate":0,"opacity":100,"size":3,"image":{"src":"static\/media\/hotspot-image\/eg7pCP83w1Qu74ZQE2Zr.png"}},"article":{"post_id":"66f625b3ae7bdf827f86d5ee","title_on_top_hide":true,"preview_box_hide":true}},"polygon":false,"post":null,"itemPrd":null,"updated_at":"2024-09-27T03:33:36.211Z","created_at":"2024-09-27T03:32:25.020Z","id":"66f62749ae7bdf608986d5f6"}],"commentScenes":[],"id":"66f4c8ed0a46d006f45efa5f"}],"posts":[{"type":"article","title":"\u200bN\u01a1i \u0111\u00e2y tr\u01b0ng b\u00e0y c\u00e1c t\u01b0 li\u1ec7u h\u00ecnh \u1ea3nh c\u1ee7a huy\u1ec7n \u0110\u1ea5t \u0110\u1ecf anh h\u00f9ng qua c\u00e1c th\u1eddi k\u1ef3 kh\u00e1ng chi\u1ebfn, ghi d\u1ea5u v\u1ec1 m\u1ed9t th\u1eddi oanh li\u1ec7t trong \u0111\u1ea5u tranh c\u00e1ch m\u1ea1ng c\u1ee7a qu\u00e2n v\u00e0 d\u00e2n ta.","slug":"noi-day-trung-bay-cac-tu-lieu-hinh-anh-cua-huyen-dat-d-anh-hung-qua-cac-thoi-ky-khang-chien-ghi-dau-ve-mot-thoi-oanh","content":"<p>\u200bN\u01a1i \u0111\u00e2y tr\u01b0ng b\u00e0y c\u00e1c t\u01b0 li\u1ec7u h\u00ecnh \u1ea3nh c\u1ee7a huy\u1ec7n \u0110\u1ea5t \u0110\u1ecf anh h\u00f9ng qua c\u00e1c th\u1eddi k\u1ef3 kh\u00e1ng chi\u1ebfn, ghi d\u1ea5u v\u1ec1 m\u1ed9t th\u1eddi oanh li\u1ec7t trong \u0111\u1ea5u tranh c\u00e1ch m\u1ea1ng c\u1ee7a qu\u00e2n v\u00e0 d\u00e2n ta.<br><\/p>","thumbnail":null,"publish":false,"updated_at":"2024-09-27T03:33:13.137Z","created_at":"2024-09-27T03:33:13.137Z","id":"66f627790a46d00b055f0999"},{"type":"article","title":"Gi\u1edbi thi\u1ec7u khu t\u01b0\u1edfng ni\u1ec7m","slug":"gioi-thieu-khu-tuong-niem-KZxbTMDO0","content":"<p>\u200b\u0110\u00e2y l\u00e0 n\u01a1i tr\u01b0ng b\u00e0y t\u01b0 li\u1ec7u h\u00ecnh \u1ea3nh v\u1ec1 cu\u1ed9c \u0111\u1eddi c\u1ee7a chi\u0323 V\u00f5 Th\u1ecb S\u00e1u t\u1eeb khi b\u1eaft \u0111\u1ea7u tham gia c\u00e1ch m\u1ea1ng cho \u0111\u1ebfn khi b\u1ecb b\u1eaft v\u00e0 hy sinh. \u0110\u1ebfn \u0111\u00e2y, ng\u01b0\u1eddi d\u00e2n v\u00e0 du kh\u00e1ch c\u00f3 th\u1ec3 ti\u1ebfp c\u1eadn c\u00e1c th\u00f4ng tin ch\u00ednh x\u00e1c v\u1ec1 ng\u01b0\u1eddi n\u01b0\u0303 Anh h\u00f9ng li\u1ec7t s\u0129 c\u1ee7a qu\u00ea h\u01b0\u01a1ng \u0110\u1ea5t \u0110\u1ecf.<br><\/p>","thumbnail":null,"publish":false,"updated_at":"2024-09-27T03:25:39.909Z","created_at":"2024-09-27T03:25:39.909Z","id":"66f625b3ae7bdf827f86d5ee"},{"type":"article","title":"Gi\u1edbi thi\u1ec7u khu t\u01b0\u1edfng ni\u1ec7m","slug":"gioi-thieu-khu-tuong-niem","content":"<p>\u200b<span style=\"font-size: 16.5px;font-family: Arial;color: rgb(34, 34, 34)\">\u0110\u1ec3 ghi nh\u1edb c\u00f4ng \u01a1n n\u1eef Anh h\u00f9ng li\u1ec7t s\u1ef9 V\u00f5 Th\u1ecb S\u00e1u v\u00e0 nh\u1eb1m gi\u00e1o d\u1ee5c truy\u1ec1n th\u1ed1ng c\u00e1ch m\u1ea1ng cho th\u1ebf h\u1ec7 tr\u1ebb, n\u0103m 1980, Huy\u1ec7n \u1ee7y, UBND huy\u1ec7n Long \u0110\u1ea5t (nay l\u00e0 huy\u1ec7n Long \u0110i\u1ec1n v\u00e0 \u0110\u1ea5t \u0110\u1ecf) \u0111\u00e3 x\u00e2y d\u1ef1ng c\u00f4ng vi\u00ean, t\u01b0\u1ee3ng \u0111\u00e0i Anh h\u00f9ng li\u1ec7t s\u1ef9 V\u00f5 Th\u1ecb S\u00e1u tr\u00ean khu \u0111\u1ea5t c\u00f3 di\u1ec7n t\u00edch 4.100 m<\/span><sup>2<\/sup><span style=\"font-size: 16.5px;font-family: Arial;color: rgb(34, 34, 34)\">ta\u0323i th\u1ecb tr\u1ea5n \u0110\u1ea5t \u0110\u1ecf. Trong c\u00f4ng vi\u00ean c\u00f3 \u0111\u1eb7t b\u1ee9c t\u01b0\u1ee3ng b\u1eb1ng \u0111\u1ed3ng cao 7m, kh\u1eafc h\u1ecda h\u00ecnh \u1ea3nh ch\u1ecb S\u00e1u ng\u1ea9ng cao \u0111\u1ea7u, hi\u00ean ngang ra ph\u00e1p tr\u01b0\u1eddng. D\u01b0\u1edbi ch\u00e2n t\u01b0\u1ee3ng \u0111\u00e0i, quanh n\u0103m h\u01b0\u01a1ng tr\u1ea7m t\u1ecfa ng\u00e1t. N\u0103m 2001, huy\u1ec7n \u0110\u1ea5t \u0110\u1ecf x\u00e2y d\u1ef1ng \u0110\u1ec1n th\u1edd V\u00f5 Th\u1ecb S\u00e1u ngay phi\u0301a sau t\u01b0\u1ee3ng \u0111\u00e0i, tr\u01b0ng b\u00e0y t\u01b0 li\u1ec7u h\u00ecnh \u1ea3nh v\u1ec1 cu\u1ed9c \u0111\u1eddi c\u1ee7a chi\u0323 S\u00e1u t\u1eeb l\u00fac b\u1eaft \u0111\u1ea7u tham gia c\u00e1ch m\u1ea1ng cho \u0111\u1ebfn khi b\u1ecb b\u1eaft, hy sinh v\u00e0 c\u00e1c h\u00ecnh \u1ea3nh li\u00ean quan c\u1ee7a huy\u1ec7n qua c\u00e1c th\u1eddi k\u1ef3.<\/span>\u200b<br><\/p>","thumbnail":null,"publish":false,"updated_at":"2024-09-27T03:14:12.868Z","created_at":"2024-09-27T03:14:12.868Z","id":"66f62304ae7bdf23a986d5e4"},{"type":"article","title":"T\u01b0\u1ee3ng \u0111\u00e0i V\u00f5 Th\u1ecb S\u00e1u","slug":"tuong-dai-vo-thi-sau","content":"<p>\u200b<span style=\"font-size: 16px;color: rgb(33, 37, 41)\">Th\u1eddi kh\u00e1ng chi\u1ebfn ch\u1ed1ng Ph\u00e1p, n\u1eef anh h\u00f9ng V\u00f5 Th\u1ecb S\u00e1u l\u00e0 ng\u01b0\u1eddi con g\u00e1i duy nh\u1ea5t b\u1ecb th\u1ef1c d\u00e2n Ph\u00e1p \u0111\u00e0y ra C\u00f4n \u0110\u1ea3o v\u00e0 h\u00e0nh h\u00ecnh t\u1ea1i \u0111\u00e2y. T\u1ea5m g\u01b0\u01a1ng anh h\u00f9ng c\u1ee7a Ch\u1ecb V\u00f5 Th\u1ecb S\u00e1u \u0111\u00e3 tr\u1edf th\u00e0nh ni\u1ec1m t\u1ef1 h\u00e0o c\u1ee7a tu\u1ed5i tr\u1ebb Vi\u1ec7t Nam. N\u1ebfu c\u00f3 \u0111\u1ebfn B\u00e0 R\u1ecba - V\u0169ng T\u00e0u, h\u00e3y gh\u00e9 vi\u1ebfng th\u0103m &nbsp;\u0110\u1ec1n th\u1edd anh h\u00f9ng li\u1ec7t s\u0129 V\u00f5 Th\u1ecb S\u00e1u, th\u0103m t\u01b0\u1ee3ng \u0111\u00e0i ch\u1ecb V\u00f5 Th\u1ecb S\u00e1u \u1edf qu\u00ea h\u01b0\u01a1ng Ch\u1ecb- &nbsp;huy\u1ec7n \u0110\u1ea5t \u0110\u1ecf, t\u1ec9nh B\u00e0 R\u1ecba - V\u0169ng T\u00e0u.<\/span>\u200b<br><\/p>","thumbnail":null,"publish":true,"updated_at":"2024-09-27T02:55:16.924Z","created_at":"2024-09-27T02:54:44.299Z","id":"66f61e740a46d084af5f097a"},{"type":"article","title":"\u200bNh\u00e0 l\u01b0u ni\u1ec7m v\u00e0 T\u01b0\u1ee3ng \u0111\u00e0i n\u1eef Anh h\u00f9ng V\u00f5 Th\u1ecb S\u00e1u","slug":"nha-luu-niem-va-tuong-dai-nu-anh-hung-vo-thi-sau","content":"<p>\u200b<span style=\"font-size: 18px\">Nh\u00e0 l\u01b0u ni\u1ec7m v\u00e0 T\u01b0\u1ee3ng \u0111\u00e0i n\u1eef Anh h\u00f9ng V\u00f5 Th\u1ecb S\u00e1u n\u1eb1m \u1edf ng\u00e3 t\u01b0 \u0110\u1ea5t \u0110\u1ecf (TT.\u0110\u1ea5t \u0110\u1ecf, huy\u1ec7n \u0110\u1ea5t \u0110\u1ecf). Nh\u00e0 l\u01b0u ni\u1ec7m tr\u01b0\u1edbc kia l\u00e0 c\u0103n nh\u00e0 \u0111\u01b0\u1ee3c gia \u0111\u00ecnh ch\u1ecb S\u00e1u thu\u00ea \u1edf khi ch\u1ecb m\u1edbi 4 tu\u1ed5i. N\u0103m 1980, ng\u00f4i nh\u00e0 \u0111\u01b0\u1ee3c tr\u00f9ng tu l\u1ea1i nguy\u00ean tr\u1ea1ng ban \u0111\u1ea7u v\u00e0 \u0111\u01b0\u1ee3c c\u00f4ng nh\u1eadn l\u00e0 Di t\u00edch L\u1ecbch s\u1eed - V\u0103n h\u00f3a c\u1ea5p qu\u1ed1c gia theo Quy\u1ebft \u0111\u1ecbnh s\u1ed1 15\/Q\u0110-BT n\u0103m 1986. Ng\u00f4i nh\u00e0 c\u00f3 l\u1ed1i ki\u1ebfn tr\u00fac \u0111\u1eb7c tr\u01b0ng c\u1ee7a l\u00e0ng qu\u00ea Vi\u1ec7t Nam, xung quanh \u0111\u01b0\u1ee3c che b\u1eb1ng c\u00e1c t\u1ea5m v\u00e1n g\u1ed7, m\u00e1i l\u1ee3p ng\u00f3i \u00e2m d\u01b0\u01a1ng. C\u0103n nh\u00e0 c\u00f3 2 ph\u00f2ng nh\u1ecf, ph\u00f2ng ngo\u00e0i \u1edf gi\u1eefa b\u00e0i tr\u00ed t\u1ee7 th\u1edd gia ti\u00ean, k\u1ebf s\u00e1t b\u00ean v\u00e1ch ph\u00eda ph\u1ea3i l\u00e0 b\u1ed9 v\u00e1n g\u1ed7. Ph\u00eda trong l\u00e0 n\u01a1i ngh\u1ec9 c\u1ee7a song th\u00e2n V\u00f5 Th\u1ecb S\u00e1u. N\u1ed1i gi\u1eefa ph\u00f2ng ngo\u00e0i v\u00e0 ph\u00f2ng trong l\u00e0 m\u1ed9t h\u00e0nh lang nh\u1ecf th\u00f4ng ra ph\u00eda sau nh\u00e0<\/span>\u200b<br><\/p>","thumbnail":{"name":"3.-CV-Vo-Thi-Sau-1024x651","type":"asset","subType":"sphere","mimetype":"image\/jpeg","deleting":false,"archived":false,"size":908496,"isFolder":false,"userChild":null,"updated_at":"2024-09-26T09:10:03.140Z","created_at":"2024-09-26T09:09:42.490Z","src":"static\/media\/asset\/WGDeIDTxtEPj3myWxe1L.jpg","src_thumb":"static\/media\/asset\/thumb\/300x_ww8mUghIEp9l9eL26RES.webp","src_preview":null,"krpano_xml":null,"id":"66f524d6ae7bdf9c6286cb64"},"publish":true,"updated_at":"2024-09-26T09:09:48.759Z","created_at":"2024-09-26T08:49:12.755Z","id":"66f52008ae7bdf25cb86cb27"}],"languages":[{"name":"Vi\u1ec7t Nam","default":true,"countryCode":"VN","hide":true,"flag":null,"id":"66f3e8390a46d00ec55ef0eb"},{"name":"English","default":false,"countryCode":"UK","hide":true,"flag":null,"id":"66f3e6d90a46d083905ef0d5"}],"keyTranslations":[],"dollhouse":null,"plugins":[{"title":"callToAction","config":{"data":[]},"updated_at":"2024-10-01T15:44:36.062Z","created_at":"2024-09-25T10:32:59.196Z","id":"66f3e6dbae7bdf61a486bea9"},{"title":"collaboration","config":{"config":{"isEnabled":false,"isPublic":true,"collaborations":""}},"updated_at":"2024-09-26T10:10:54.562Z","created_at":"2024-09-25T10:32:59.202Z","id":"66f3e6dbae7bdf692a86beab"},{"title":"controlbar","config":{"config":{"floorplan":{"isHide":false,"type":"icon","icon":"far fa-layer-group"},"sound_project_on":{"isHide":false,"type":"icon","icon":"far fa-volume"},"sound_project_off":{"isHide":false,"type":"icon","icon":"far fa-volume-mute"},"auto_rotate_on":{"isHide":false,"type":"icon","icon":"far fa-repeat"},"auto_rotate_off":{"isHide":false,"type":"icon","icon":"fal fa-repeat"},"home":{"isHide":false,"type":"icon","icon":"far fa-home"},"auto_change_scene_on":{"isHide":false,"type":"icon","icon":"far fa-pause"},"auto_change_scene_off":{"isHide":false,"type":"icon","icon":"far fa-play"},"sound_scene_on":{"isHide":false,"type":"icon","icon":"far fa-volume-up"},"sound_scene_off":{"isHide":false,"type":"icon","icon":"far fa-volume-off"},"view_mode":{"isHide":false,"type":"icon","icon":"far fa-eye"},"multi_staging":{"isHide":false,"type":"icon","icon":"far fa-images"},"gyro":{"isHide":false,"type":"icon","icon":"far fa-hurricane"},"vr":{"isHide":false,"type":"icon","icon":"far fa-head-vr"},"fullscreen":{"isHide":false,"type":"icon","icon":"far fa-expand-arrows-alt"},"map":{"isHide":false,"type":"icon","icon":"far fa-map-marked-alt"},"info_scene":{"isHide":false,"type":"icon","icon":"far fa-info"},"info_tour":{"isHide":false,"type":"icon","icon":"far fa-file-alt"},"group_auto_play":{"isHide":false,"type":"icon","icon":"far fa-play"},"view_mode_normal":{"isHide":false,"type":"icon","icon":"far fa-mountains"},"view_mode_little_planet":{"isHide":false,"type":"icon","icon":"far fa-globe-asia"},"view_mode_mirror":{"isHide":false,"type":"icon","icon":"far fa-globe"},"screenshot_capture":{"isHide":false,"type":"icon","icon":"far fa-camera-viewfinder"},"multi_language":{"isHide":false,"type":"icon","icon":"far fa-language"},"dollhouse":{"isHide":false,"type":"icon","icon":"far fa-kaaba"}}},"updated_at":"2024-09-26T10:16:04.631Z","created_at":"2024-09-25T10:32:59.202Z","id":"66f3e6dbae7bdfb02c86beaa"},{"title":"copyRight","config":{"config":{"isEnabled":true,"description":"Th\u1ef1c hi\u1ec7n b\u1edfi","link":"https:\/\/igb.vn","author":"IGB Group"}},"updated_at":"2024-09-26T09:35:29.778Z","created_at":"2024-09-25T10:32:59.206Z","id":"66f3e6db0a46d0398b5ef0d7"},{"title":"floorplan","config":{"data":[],"config":{"isShowOnStart":true,"bgColor":"rgb(253,202,110)","floorplan":{"type":"box","position":"topRight"},"marker":{"bgColor":"#007afe","borderColor":"#fff"},"radar":{"isEnabled":true,"bgColor":"#007afe40","borderColor":"#fff","borderWidth":1,"width":48}}},"updated_at":"2024-09-28T10:56:58.882Z","created_at":"2024-09-25T10:32:59.192Z","id":"66f3e6dbae7bdf5b6a86bea6"},{"title":"formCapture","config":{"data":[],"config":[]},"updated_at":"2024-09-26T10:13:22.572Z","created_at":"2024-09-25T10:32:59.211Z","id":"66f3e6db0a46d045b05ef0da"},{"title":"logo","config":{"config":{"isEnabled":true,"image":"static\/media\/asset\/PRXcMuYXIbo5LAp2fSKu.png","url":"","size":70,"position":"topLeft"}},"updated_at":"2024-10-01T15:44:56.316Z","created_at":"2024-09-25T10:32:59.196Z","id":"66f3e6dbae7bdf04ef86bea7"},{"title":"map","config":{"data":{"markers":[{"id":"7kas7_WlI6TdvYj9aY_6C","lat":10.48946219573937,"lng":107.26858258849066,"target_scene_id":"66f4c8ed0a46d037f35efa61"},{"id":"9aRZ44lVZd0-kPY7CnbdN","lat":10.48924065531746,"lng":107.2687327921955,"target_scene_id":"66f4c8edae7bdfe70c86c810"},{"id":"E56I9piLSAAAshu-00VaB","lat":10.489230105769591,"lng":107.26860404616278,"target_scene_id":"66f4c8edae7bdf3e0e86c811"},{"id":"rB0auTvEVCDEhcS5bGQ2f","lat":10.489071862508606,"lng":107.26845384245794,"target_scene_id":"66f4c8edae7bdf641e86c80f"},{"id":"YJov8CHli1MMUNEhRdQ8Z","lat":10.488801067302255,"lng":107.2688793723996,"target_scene_id":"66f4c8ed0a46d08d955efa60"},{"id":"ZQL2f2CRCQ8rL8qu6j0fv","lat":10.488864364671759,"lng":107.26872916869476,"target_scene_id":"66f4c8ed0a46d022d85efa5e"},{"id":"-1wDsM6lg6ez5MpwszHVN","lat":10.488832715988629,"lng":107.26905103377655,"target_scene_id":"66f4c8ed0a46d006f45efa5f"}]},"config":{"isEnabled":true,"isShowOnStart":true,"mapStyle":"","mapType":"terrain","map":{"type":"box"},"marker":{"src":""},"radar":{"isEnabled":true,"bgColor":"rgba(226,111,85,0.7)","borderColor":"#fff","borderWidth":1,"width":80},"bgColor":"rgb(1,104,177)"}},"updated_at":"2024-10-01T15:44:07.874Z","created_at":"2024-09-25T10:32:59.206Z","id":"66f3e6db0a46d054145ef0d8"},{"title":"nadir","config":{"config":{"isEnabled":false,"scale":1,"src":"","link":""}},"updated_at":"2024-09-27T04:37:13.232Z","created_at":"2024-09-25T10:32:59.206Z","id":"66f3e6db0a46d070725ef0d9"},{"title":"popupIntro","config":{"config":{"isEnabled":false,"type":"image","isAutoClose":false,"timeAutoClose":2,"textClose":"Close","mode":"fullscreen","imageDesktop":"static\/media\/asset\/izIMpV329bfYlB29gg0W.png"}},"updated_at":"2024-09-29T04:33:28.220Z","created_at":"2024-09-25T10:32:59.206Z","id":"66f3e6db0a46d0b4125ef0d6"},{"title":"protectPassword","config":{"config":{"isEnabled":false,"password":""}},"updated_at":"2024-09-25T10:32:59.196Z","created_at":"2024-09-25T10:32:59.196Z","id":"66f3e6dbae7bdf3cd786bea8"},{"title":"screenshotCapture","config":{"config":{"isOffWatermark":false}},"updated_at":"2024-10-01T15:41:15.175Z","created_at":"2024-09-25T10:32:59.211Z","id":"66f3e6db0a46d014b35ef0db"}],"groups":[{"name":"Khu\u00f4n vi\u00ean","sort":2,"updated_at":"2024-10-01T08:10:31.442Z","created_at":"2024-09-26T02:46:07.997Z","id":"66f4caefae7bdf7a8d86c820"},{"name":"Khu t\u01b0\u1edfng ni\u1ec7m","sort":3,"updated_at":"2024-10-01T08:10:31.447Z","created_at":"2024-09-26T02:46:49.303Z","id":"66f4cb190a46d0ebac5efa69"}],"id":"66f3e6d90a46d09e185ef0d4"}